setup.cfg
setup.py
./__init__.py
./configuration.py
./fabfile.py
./party.py
./tests/__init__.py
./tests/test_sugarcrm.py
trytond_sugarcrm.egg-info/PKG-INFO
trytond_sugarcrm.egg-info/SOURCES.txt
trytond_sugarcrm.egg-info/dependency_links.txt
trytond_sugarcrm.egg-info/entry_points.txt
trytond_sugarcrm.egg-info/not-zip-safe
trytond_sugarcrm.egg-info/requires.txt
trytond_sugarcrm.egg-info/top_level.txt