Metadata-Version: 1.0
Name: trytond-sugarcrm
Version: 2.6.1.0
Summary: SugarCRM Integration
Home-page: http://openlabs.co.in/article/tryton-sugar-crm-integration-module
Author: Openlabs Technologies and Consulting P Ltd.
Author-email: UNKNOWN
License: GPL-3
Download-URL: https://github.com/openlabs/trytond-sugarcrm
Platform: UNKNOWN
Classifier: Development Status :: 5 - Production/Stable
Classifier: Environment :: Plugins
Classifier: Framework :: Tryton
Classifier: Intended Audience :: Developers
Classifier: Intended Audience :: Financial and Insurance Industry
Classifier: Intended Audience :: Legal Industry
Classifier: Intended Audience :: Manufacturing
Classifier: License :: OSI Approved :: GNU General Public License (GPL)
Classifier: Natural Language :: English
Classifier: Operating System :: OS Independent
Classifier: Programming Language :: Python :: 2.6
Classifier: Programming Language :: Python :: 2.7
Classifier: Topic :: Office/Business
